odoo/addons/mrp_sale_info/README.rst
odoo/addons/mrp_sale_info/__init__.py
odoo/addons/mrp_sale_info/__manifest__.py
odoo/addons/mrp_sale_info/i18n/de.po
odoo/addons/mrp_sale_info/i18n/es.po
odoo/addons/mrp_sale_info/i18n/fr.po
odoo/addons/mrp_sale_info/i18n/mrp_sale_info.pot
odoo/addons/mrp_sale_info/i18n/pt_BR.po
odoo/addons/mrp_sale_info/i18n/zh_CN.po
odoo/addons/mrp_sale_info/models/__init__.py
odoo/addons/mrp_sale_info/models/mrp_production.py
odoo/addons/mrp_sale_info/models/mrp_workorder.py
odoo/addons/mrp_sale_info/static/description/icon.png
odoo/addons/mrp_sale_info/views/mrp_production.xml
odoo/addons/mrp_sale_info/views/mrp_workorder.xml
odoo11_addon_mrp_sale_info-11.0.1.0.0.99.dev2.dist-info/METADATA
odoo11_addon_mrp_sale_info-11.0.1.0.0.99.dev2.dist-info/RECORD
odoo11_addon_mrp_sale_info-11.0.1.0.0.99.dev2.dist-info/WHEEL
odoo11_addon_mrp_sale_info-11.0.1.0.0.99.dev2.dist-info/top_level.txt
